{
  "metadata": {
    "provider": "Oxford University Press"
  },
  "results": [
    {
      "id": "or",
      "language": "en",
      "lexicalEntries": [
        {
          "entries": [
            {
              "etymologies": [
                "Middle English: a reduced form of the obsolete conjunction other (which superseded Old English oththe \u2018or\u2019), of uncertain ultimate origin"
              ],
              "homographNumber": "100",
              "notes": [
                {
                  "text": "Where a verb follows a list separated by or, the traditional rule is that the verb should be singular, as long as the things in the list are individually singular, as in a sandwich or other snack is included in the price (rather than a sandwich or other snack are included in the price). The argument is that each of the elements agrees separately with the verb. The opposite rule applies when the elements are joined by and: here, the verb should be plural: a sandwich and a cup of coffee are included in the price. These traditional rules are observed in good English writing style but are often disregarded in speech. On the use of either \u2026 or, see either",
                  "type": "editorialNote"
                }
              ],
              "senses": [
                {
                  "definitions": [
                    "used to link alternatives"
                  ],
                  "examples": [
                    {
                      "text": "it doesn't matter whether the theory is right or wrong"
                    },
                    {
                      "text": "are you coming or not?"
                    },
                    {
                      "text": "a cup of tea or coffee"
                    },
                    {
                      "text": "I either take taxis or walk everywhere"
                    }
                  ],
                  "id": "m_en_gbus0724140.006",
                  "short_definitions": [
                    "linking alternatives"
                  ]
                },
                {
                  "definitions": [
                    "introducing a synonym or explanation of a preceding word or phrase"
                  ],
                  "examples": [
                    {
                      "text": "yoga is a series of postures, or asanas"
                    }
                  ],
                  "id": "m_en_gbus0724140.009",
                  "short_definitions": [
                    "introducing synonym or explanation"
                  ]
                },
                {
                  "definitions": [
                    "otherwise (used to introduce the consequences of something not being done or not being the case)"
                  ],
                  "examples": [
                    {
                      "text": "hurry up, or you'll miss it all"
                    }
                  ],
                  "id": "m_en_gbus0724140.011",
                  "short_definitions": [
                    "otherwise"
                  ],
                  "thesaurusLinks": [
                    {
                      "entry_id": "otherwise",
                      "sense_id": "t_en_gb0010414.001"
                    }
                  ]
                },
                {
                  "definitions": [
                    "introducing an afterthought, usually in the form of a question"
                  ],
                  "examples": [
                    {
                      "text": "John's indifference\u2014or was it?\u2014left her unsettled"
                    }
                  ],
                  "id": "m_en_gbus0724140.013",
                  "short_definitions": [
                    "introducing afterthought"
                  ]
                },
                {
                  "definitions": [
                    "either"
                  ],
                  "examples": [
                    {
                      "text": "to love is the one way to know or God or man"
                    }
                  ],
                  "id": "m_en_gbus0724140.015",
                  "registers": [
                    "archaic"
                  ],
                  "short_definitions": [
                    "either"
                  ]
                }
              ]
            }
          ],
          "language": "en",
          "lexicalCategory": "Conjunction",
          "pronunciations": [
            {
              "audioFile": "http://audio.oxforddictionaries.com/en/mp3/_or_1_gb_2.mp3",
              "dialects": [
                "British English"
              ],
              "phoneticNotation": "IPA",
              "phoneticSpelling": "\u0254\u02d0"
            }
          ],
          "text": "or"
        },
        {
          "entries": [
            {
              "grammaticalFeatures": [
                {
                  "text": "Singular",
                  "type": "Number"
                }
              ],
              "homographNumber": "101",
              "notes": [
                {
                  "text": "Where a verb follows a list separated by or, the traditional rule is that the verb should be singular, as long as the things in the list are individually singular, as in a sandwich or other snack is included in the price (rather than a sandwich or other snack are included in the price). The argument is that each of the elements agrees separately with the verb. The opposite rule applies when the elements are joined by and: here, the verb should be plural: a sandwich and a cup of coffee are included in the price. These traditional rules are observed in good English writing style but are often disregarded in speech. On the use of either \u2026 or, see either",
                  "type": "editorialNote"
                }
              ],
              "senses": [
                {
                  "definitions": [
                    "a logical operation which gives the value one if at least one operand has the value one, and otherwise gives a value of zero."
                  ],
                  "domains": [
                    "Computing",
                    "Electronics"
                  ],
                  "id": "m_en_gbus0724140.017",
                  "notes": [
                    {
                      "text": "\"OR\"",
                      "type": "wordFormNote"
                    }
                  ],
                  "short_definitions": [
                    "logical operation which gives value one if at least one operand has value one"
                  ],
                  "subsenses": [
                    {
                      "definitions": [
                        "denoting a gate circuit which produces an output if there is a signal on any of its inputs."
                      ],
                      "domains": [
                        "Electronics"
                      ],
                      "id": "m_en_gbus0724140.019",
                      "notes": [
                        {
                          "text": "as modifier",
                          "type": "grammaticalNote"
                        }
                      ],
                      "short_definitions": [
                        "denoting gate circuit which produces output if there is signal on any of its inputs"
                      ],
                      "variantForms": [
                        {
                          "text": "OR gate"
                        }
                      ]
                    }
                  ]
                }
              ]
            },
            {
              "etymologies": [
                "early 16th century: from French, from Latin aurum \u2018gold\u2019"
              ],
              "grammaticalFeatures": [
                {
                  "text": "Mass",
                  "type": "Countability"
                },
                {
                  "text": "Singular",
                  "type": "Number"
                }
              ],
              "homographNumber": "200",
              "senses": [
                {
                  "definitions": [
                    "gold or yellow, as a heraldic tincture"
                  ],
                  "domains": [
                    "Heraldry"
                  ],
                  "examples": [
                    {
                      "text": "a bend or"
                    }
                  ],
                  "id": "m_en_gbus0724160.005",
                  "short_definitions": [
                    "gold or yellow, as heraldic tincture"
                  ]
                }
              ]
            }
          ],
          "language": "en",
          "lexicalCategory": "Noun",
          "pronunciations": [
            {
              "audioFile": "http://audio.oxforddictionaries.com/en/mp3/_or_1_gb_2.mp3",
              "dialects": [
                "British English"
              ],
              "phoneticNotation": "IPA",
              "phoneticSpelling": "\u0254\u02d0"
            }
          ],
          "text": "or"
        },
        {
          "entries": [
            {
              "grammaticalFeatures": [
                {
                  "text": "Abbreviation",
                  "type": "Residual"
                }
              ],
              "homographNumber": "400",
              "senses": [
                {
                  "definitions": [
                    "operational research."
                  ],
                  "domains": [
                    "Commerce"
                  ],
                  "id": "m_en_gbus0724130.004",
                  "short_definitions": [
                    "operational research"
                  ]
                },
                {
                  "definitions": [
                    "Oregon (in official postal use)."
                  ],
                  "domains": [
                    "Postal"
                  ],
                  "id": "m_en_gbus0724130.007",
                  "short_definitions": [
                    "Oregon"
                  ]
                },
                {
                  "definitions": [
                    "other ranks (as opposed to commissioned officers)."
                  ],
                  "domains": [
                    "Military"
                  ],
                  "id": "m_en_gbus0724130.009",
                  "regions": [
                    "British"
                  ],
                  "short_definitions": [
                    "other ranks"
                  ]
                }
              ]
            }
          ],
          "language": "en",
          "lexicalCategory": "Residual",
          "text": "OR"
        }
      ],
      "type": "headword",
      "word": "or"
    }
  ]
}