{
  "metadata": {
    "provider": "Oxford University Press"
  },
  "results": [
    {
      "id": "did",
      "language": "en",
      "lexicalEntries": [
        {
          "entries": [
            {
              "homographNumber": "000",
              "senses": [
                {
                  "crossReferenceMarkers": [
                    "past of do"
                  ],
                  "crossReferences": [
                    {
                      "id": "do",
                      "text": "do",
                      "type": "see also"
                    }
                  ],
                  "id": "m_en_gbus0273860.005"
                }
              ]
            }
          ],
          "language": "en",
          "lexicalCategory": "Other",
          "pronunciations": [
            {
              "audioFile": "http://audio.oxforddictionaries.com/en/mp3/did_gb_2.mp3",
              "dialects": [
                "British English"
              ],
              "phoneticNotation": "IPA",
              "phoneticSpelling": "d\u026ad"
            }
          ],
          "text": "did"
        }
      ],
      "type": "headword",
      "word": "did"
    }
  ]
}